frequency_division/divide_by_3.sv
/* Write RTL to perform frequency division by 3 */

// Frequency division with 33% duty cycle - High for 1 cycle and low for 2 cycles
module divide_by_3_33(
    input clk, 
    input rst_n,
    output clk_3_33
);
    logic [1:0] counter;

    always_ff @(posedge clk or negedge rst_n) begin
        if(!rst_n) begin
            counter <= 0;
        end
        else if(counter == 2'b10) begin
            counter <= 0;
        end
        else begin
            counter <= counter + 1;
        end
    end

    assign clk_3_33 = (counter==2'b01);
endmodule

// Frequency division with 50% duty cycle - Equal number of high and low cycles
module divide_by_3_50(
    input clk, 
    input rst_n,
    output clk_3_50
);

    logic pos_pulse; //33% duty cycle
    logic neg_pulse; //33% duty cycle but delayed
    logic [1:0] counter;

    // Counter logic
    always_ff @(posedge clk or negedge rst_n) begin
        if(!rst_n) begin
            counter <= 0;
        end
        else if(counter == 2'b10) begin
            counter <= 0;
        end
        else begin
            counter <= counter + 1;
        end
    end

    // Create a 33% duty cycle pulse
    always_ff @(posedge clk or negedge rst_n) begin
        if(!rst_n) begin
            pos_pulse <= 0;
        end
        else if(counter == 2'd00) begin
            pos_pulse <= 1;
        end
        else begin
            pos_pulse <= 0;
        end
    end

    // Delay pos_pulse
    always_ff @(negedge clk or negedge rst_n) begin
        if(!rst_n) begin
            neg_pulse <= 0;
        end
        else neg_pulse <= pos_pulse;
    end

    assign clk_3_50 = pos_pulse | neg_pulse;

endmodule

module test;
    logic clk; 
    logic rst_n;
    logic clk_3_33;
    logic clk_3_50;

    initial clk = 0;
    always #5 clk = ~clk;

    divide_by_3_33 dut1(.*);
    divide_by_3_50 dut2(.*);

    initial begin
        $dumpfile("waves/div_by_3.vcd");
        $dumpvars(0, test);

        rst_n = 0;
        repeat(2) @(posedge clk);
        rst_n = 1;

        repeat(20) @(posedge clk); 
        $finish;
    end
endmodule

frequency_division/waves/div_by_3.vcd
$date
    Jul 25, 2026  21:44:15
$end
$version
    TOOL:	xmsim	22.03-s012
$end
$timescale
    1 ns
$end

$scope module test $end
$var reg       1 !    clk $end
$var reg       1 "    rst_n $end
$var reg       1 #    clk_3_33 $end
$var reg       1 $    clk_3_50 $end

$scope module dut1 $end
$var wire      1 %    clk  $end
$var wire      1 &    rst_n  $end
$var wire      1 '    clk_3_33  $end
$var reg       2 (    counter [1:0] $end
$upscope $end


$scope module dut2 $end
$var wire      1 )    clk  $end
$var wire      1 *    rst_n  $end
$var wire      1 +    clk_3_50  $end
$var reg       1 ,    pos_pulse $end
$var reg       1 -    neg_pulse $end
$var reg       2 .    counter [1:0] $end
$upscope $end

$upscope $end

$enddefinitions $end
$dumpvars
0!
0"
0#
0$
0%
0&
0'
b0 (
0)
0*
0+
0,
0-
b0 .
$end
#5
1!
1)
1%
#10
0!
0)
0%
#15
1!
1"
1*
1&
1)
1%
b1 .
1,
b1 (
1'
1+
1#
1$
#20
0!
0)
0%
1-
#25
1!
1)
1%
b10 .
0,
b10 (
0'
0#
#30
0!
0)
0%
0-
0+
0$
#35
1!
1)
1%
b0 .
b0 (
#40
0!
0)
0%
#45
1!
1)
1%
b1 .
1,
b1 (
1'
1+
1#
1$
#50
0!
0)
0%
1-
#55
1!
1)
1%
b10 .
0,
b10 (
0'
0#
#60
0!
0)
0%
0-
0+
0$
#65
1!
1)
1%
b0 .
b0 (
#70
0!
0)
0%
#75
1!
1)
1%
b1 .
1,
b1 (
1'
1+
1#
1$
#80
0!
0)
0%
1-
#85
1!
1)
1%
b10 .
0,
b10 (
0'
0#
#90
0!
0)
0%
0-
0+
0$
#95
1!
1)
1%
b0 .
b0 (
#100
0!
0)
0%
#105
1!
1)
1%
b1 .
1,
b1 (
1'
1+
1#
1$
#110
0!
0)
0%
1-
#115
1!
1)
1%
b10 .
0,
b10 (
0'
0#
#120
0!
0)
0%
0-
0+
0$
#125
1!
1)
1%
b0 .
b0 (
#130
0!
0)
0%
#135
1!
1)
1%
b1 .
1,
b1 (
1'
1+
1#
1$
#140
0!
0)
0%
1-
#145
1!
1)
1%
b10 .
0,
b10 (
0'
0#
#150
0!
0)
0%
0-
0+
0$
#155
1!
1)
1%
b0 .
b0 (
#160
0!
0)
0%
#165
1!
1)
1%
b1 .
1,
b1 (
1'
1+
1#
1$
#170
0!
0)
0%
1-
#175
1!
1)
1%
b10 .
0,
b10 (
0'
0#
#180
0!
0)
0%
0-
0+
0$
#185
1!
1)
1%
b0 .
b0 (
#190
0!
0)
0%
#195
1!
1)
1%
b1 .
1,
b1 (
1'
1+
1#
1$
#200
0!
0)
0%
1-
#205
1!
1)
1%
b10 .
0,
b10 (
0'
0#
#210
0!
0)
0%
0-
0+
0$
