low_power_rtl/glitch_free_enable_clock_gating.sv
module clock_gating(
    input clk, 
    input enable,
    output clk_out
);
    // Use a negative level sensitive latch
    logic enable_latched;

    always_latch begin
        if(!clk) begin
            enable_latched <= enable;
        end
    end
    
    assign clk_out = clk & enable_latched;
endmodule

module test;
    logic clk;
    logic enable;
    logic clk_out;

    // Clock Generation: 10ns Clock Period, 100 MHz
    initial clk = 0;
    always #5 clk = ~clk;

    clock_gating dut(.*);

    initial begin
        $dumpfile("waves/glitch_free_enable_clock_gating.vcd");
        $dumpvars(1, test);
    end

    initial begin
        enable = 0;
        #20;
        enable = 1;
        #7;
        enable = 0;
        #12;
        enable  = 1;
        #8;
        enable = 0;
        #30;
        enable = 1;
        $finish;
    end
endmodule

low_power_rtl/waves/enable_clock_gating.vcd
$date
    Jul 25, 2026  15:06:58
$end
$version
    TOOL:	xmsim	22.03-s012
$end
$timescale
    1 ns
$end

$scope module test $end
$var reg       1 !    clk $end
$var reg       1 "    enable $end
$var reg       1 #    clk_out $end
$upscope $end

$enddefinitions $end
$dumpvars
0!
0"
0#
$end
#5
1!
#10
0!
#15
1!
#20
1"
0!
#25
1!
1#
#30
0!
0#
#35
1!
1#
#40
0"
0!
0#
#45
1!
#50
0!
#55
1!
#60
0!
#65
1!
#70
1"
0!
#72
0"
#75
1!
#80
0!
#85
1!
#90
0!
#92
1"
#95
1!
1#
#99
0"
0#
#100
0!
#105
1!
#110
0!
#111
1"
#115
1!
1#
#119
0"
0#
#120
0!
#125
1!
#130
0!
#135
1!
#140
0!
#145
1!
#149
1"
