low_power_rtl/xor_clock_gating.sv
/********************

XOR Clock Gating

- The problem we solve with XOR based clock gating is for redundant register writes.
- Imagine we have a register that doesn't have an explicit write-enable signal
- If the input to the register is always the same for 100 consecutive clock cycles, in that case
  we have to rewrite the same value to the register over and over again. This consumes lot of dynamic power

Example code:

always_ff @(posedge clk) begin
    q <= d;
end

- If value is 8'hAA for 100 clock cycles, then each cycle we have to re-write with the same value
- This could be easily solved with the following adjustment

if(q!=d) begin  
    q <= d;
end

- This means we only perform the write when a new value arrives. However, during synthesis this will
  create a multiplexer. 
  1) select d when q != d 
  2) select q when q == d

- The other issue is the clock pin is still toggling even when there is a redundant write. That means it will
  continue to consume dynamic power

How XOR Clock Gating Solves

- Using the XOR of d and q, we will create an xor_enable signal which will then be fed as the input to the 
  clock gating cell's enable input to generate a gated clock
- The register now get's triggered on posedge of gated clock

*********************/

module clock_gating(
    input in_clk, 
    input enable,
    output gated_clk
);
    logic enable_latched;

    always_latch begin
        if(!in_clk) begin
            enable_latched <= enable;
        end
    end

    assign gated_clk = in_clk & enable_latched;
endmodule

module xor_gating(
    input        clk, 
    input        rst_n,
    input  logic [7:0]  d,
    output logic [7:0] q 
);
    logic xor_enable;
    logic gated_clk;

    assign xor_enable = !rst_n ? 1'b1 : |(d ^ q);

    clock_gating icg(
        .in_clk(clk),
        .enable(xor_enable),
        .gated_clk(gated_clk)
    );

    always_ff @(posedge gated_clk) begin
        if(!rst_n) begin
            q <= 8'h0;
        end
        else q <= d;
    end


endmodule

module test;
    logic clk;
    logic [7:0] d;
    logic rst_n;
    logic [7:0] q;

    initial clk = 0;
    always #5 clk = ~clk;

    xor_gating dut(.*);

    initial begin
        $dumpfile("waves/xor_gating.vcd");
        $dumpvars(0,test);
    end

    initial begin
        
        rst_n = 0;
        d=0;
        repeat(2) @(posedge clk);
        rst_n = 1;
        repeat(5) begin
            @(posedge clk);
            d <= 8'h66;
        end

        repeat(10) begin
            @(posedge clk);
            d <= $urandom();
        end

        $finish;

    end
endmodule

low_power_rtl/waves/xor_gating.vcd
$date
    Jul 25, 2026  16:48:56
$end
$version
    TOOL:	xmsim	22.03-s012
$end
$timescale
    1 ns
$end

$scope module test $end
$var reg       1 !    clk $end
$var reg       8 "    d [7:0] $end
$var reg       1 #    rst_n $end
$var reg       8 $    q [7:0] $end

$scope module dut $end
$var wire      1 %    clk  $end
$var wire      1 &    rst_n  $end
$var wire      8 '    d [7:0] $end
$var reg       8 (    q [7:0] $end
$var reg       1 )    xor_enable $end
$var reg       1 *    gated_clk $end

$scope module icg $end
$var wire      1 %    in_clk  $end
$var wire      1 +    enable  $end
$var wire      1 ,    gated_clk  $end
$var reg       1 -    enable_latched $end
$upscope $end

$upscope $end

$upscope $end

$enddefinitions $end
$dumpvars
0!
b0 "
0#
bx $
0%
0&
b0 '
bx (
1)
0*
1+
0,
1-
$end
#5
1!
1%
1,
1*
b0 (
b0 $
#10
0!
0%
0,
0*
#15
1!
1#
1&
1%
0)
1,
0+
1*
#20
0!
0%
0,
0*
0-
#25
1!
1%
b1100110 "
b1100110 '
1)
1+
#30
0!
0%
1-
#35
1!
1%
1,
1*
b1100110 (
0)
0+
b1100110 $
#40
0!
0%
0,
0*
0-
#45
1!
1%
#50
0!
0%
#55
1!
1%
#60
0!
0%
#65
1!
1%
#70
0!
0%
#75
1!
1%
b110101 "
b110101 '
1)
1+
#80
0!
0%
1-
#85
1!
1%
1,
1*
b11110010 "
b110101 (
0)
0+
b11110010 '
1)
b110101 $
1+
#90
0!
0%
0,
0*
#95
1!
1%
1,
1*
b111111 "
b11110010 (
0)
0+
b111111 '
1)
b11110010 $
1+
#100
0!
0%
0,
0*
#105
1!
1%
1,
1*
b10101000 "
b111111 (
0)
0+
b10101000 '
1)
b111111 $
1+
#110
0!
0%
0,
0*
#115
1!
1%
1,
1*
b11010100 "
b10101000 (
0)
0+
b11010100 '
1)
b10101000 $
1+
#120
0!
0%
0,
0*
#125
1!
1%
1,
1*
b1100 "
b11010100 (
0)
0+
b1100 '
1)
b11010100 $
1+
#130
0!
0%
0,
0*
#135
1!
1%
1,
1*
b10111 "
b1100 (
0)
0+
b10111 '
1)
b1100 $
1+
#140
0!
0%
0,
0*
#145
1!
1%
1,
1*
b1011001 "
b10111 (
0)
0+
b1011001 '
1)
b10111 $
1+
#150
0!
0%
0,
0*
#155
1!
1%
1,
1*
b11 "
b1011001 (
0)
0+
b11 '
1)
b1011001 $
1+
