digital_blocks/full_adder.sv
/**** Full Adder ***/

module full_adder_behavioral(
    input a,
    input b,
    input cin, 
    output logic sum_behavioral, 
    output logic carry_behavioral
);

    always_comb begin
        {carry_behavioral, sum_behavioral} = a+b+cin;
    end

endmodule


module full_adder_dataflow(
    input a,
    input b,
    input cin, 
    output sum_dataflow, 
    output carry_dataflow
);

    assign sum_dataflow = a ^ b ^ cin;
    assign carry_dataflow = (a & b) | (a & cin) | (cin & b);
endmodule


module test;
    logic a, b, cin;
    logic sum_behavioral, carry_behavioral, sum_dataflow, carry_dataflow;

    full_adder_behavioral dut1(.*);
    full_adder_dataflow dut2(.*);

    initial begin
        $dumpfile("waves/full_adder.vcd");
        $dumpvars(1, test);
        a = 0;
        b = 0;
        cin = 0;
        #1;
        repeat(12) begin
            a = $urandom_range(0,1);
            b = $urandom_range(0,1);
            cin = $urandom_range(0,1);

            #1;
        end

    end
endmodule

digital_blocks/waves/full_adder.vcd
$date
    Jul 28, 2026  16:46:36
$end
$version
    TOOL:	xmsim	22.03-s012
$end
$timescale
    1 ns
$end

$scope module test $end
$var reg       1 !    a $end
$var reg       1 "    b $end
$var reg       1 #    cin $end
$var reg       1 $    sum_behavioral $end
$var reg       1 %    carry_behavioral $end
$var reg       1 &    sum_dataflow $end
$var reg       1 '    carry_dataflow $end
$upscope $end

$enddefinitions $end
$dumpvars
0!
0"
0#
0$
0%
0&
0'
$end
#1
1"
1&
1$
#2
1!
1'
0&
1%
0$
#3
0"
0'
1&
0%
1$
#6
0!
1"
1#
1'
0&
1%
0$
#7
1!
0"
#8
1"
0#
#9
0!
0"
0'
0%
#10
1#
1&
1$
#11
1!
1"
1'
1%
#12
0"
0&
0$
