fsm/sequence_detector_101011.sv
/***** Basic Verilog question - Write a Sequence Detector for 101011 *****/

// This is a registered mealy machine logic. 

module fsm(
    input clk,
    input rst_n,
    input in, 
    output logic detect
);
    
    typedef enum logic[2:0] {
        IDLE, 
        S1,
        S10,
        S101,
        S1010,
        S10101
    } state_t;

    state_t state, next_state;
    logic next_detect;

    always_ff @(posedge clk or negedge rst_n) begin
        if(!rst_n) begin
            state <= IDLE;
            detect <= 0;
        end
        else begin
            state <= next_state;
            detect <= next_detect;
        end
    end

    always_comb begin
        next_state = IDLE;
        next_detect = 0;
        case(state)
            IDLE: begin
                next_state = in ? S1: IDLE;
            end
            S1: begin
                next_state = in ? S1: S10;
            end
            S10: begin
                next_state = in ? S101: IDLE;
            end
            S101: begin
                next_state = in ? S1: S1010;
            end
            S1010: begin
                next_state = in ? S10101: IDLE;
            end
            S10101: begin
                next_state = in ? S1: S1010;
                next_detect = in?1:0;
            end
        endcase
    end
endmodule

module test;
    logic clk;
    logic rst_n;
    logic in;
    logic detect;
    logic input_test_data[] = '{1,0,1,0,1,1,1,0,1,0,0,0,1,0,1,0,1,1,0,0,1,1,1,1,0,1};

    fsm dut(.*);

    initial begin
        $dumpfile("waves/fsm_101011.vcd");
        $dumpvars(1, test);
    end

    initial clk = 0;
    always #5 clk = ~clk;

    initial begin
        rst_n = 0;
        in = 0;
        repeat(2) @(negedge clk);
        rst_n = 1;
        
        foreach(input_test_data[i]) begin
            @(negedge clk);
            in = input_test_data[i];
        end

        @(posedge clk);
        $finish;
    end
endmodule

fsm/waves/fsm_101011.vcd
$date
    Aug 31, 2026  11:57:47
$end
$version
    TOOL:	xmsim	22.03-s012
$end
$timescale
    1 ns
$end

$scope module test $end
$var reg       1 !    clk $end
$var reg       1 "    rst_n $end
$var reg       1 #    in $end
$var reg       1 $    detect $end
$upscope $end

$enddefinitions $end
$dumpvars
0!
0"
0#
0$
$end
#5
1!
#10
0!
#15
1!
#20
0!
1"
#25
1!
#30
0!
1#
#35
1!
#40
0!
0#
#45
1!
#50
0!
1#
#55
1!
#60
0!
0#
#65
1!
#70
0!
1#
#75
1!
#80
0!
#85
1!
1$
#90
0!
#95
1!
0$
#100
0!
0#
#105
1!
#110
0!
1#
#115
1!
#120
0!
0#
#125
1!
#130
0!
#135
1!
#140
0!
#145
1!
#150
0!
1#
#155
1!
#160
0!
0#
#165
1!
#170
0!
1#
#175
1!
#180
0!
0#
#185
1!
#190
0!
1#
#195
1!
#200
0!
#205
1!
1$
#210
0!
0#
#215
1!
0$
#220
0!
#225
1!
#230
0!
1#
#235
1!
#240
0!
#245
1!
#250
0!
#255
1!
#260
0!
#265
1!
#270
0!
0#
#275
1!
#280
0!
1#
