fsm/sequence_detector_10X011.sv
/*
Design a circuit that can detect 10X011 (X can be either 0 or 1)

Below is a moore machine fsm design for the sequence detector. 
*/

module fsm(
    input clk, 
    input rst_n,
    input in, 
    output detect
);

    typedef enum logic[2:0] {
        IDLE,
        S1,
        S10,
        S10X,
        S10X0,
        S10X01,
        FINAL
    } state_t;

    state_t state, next_state;

    always_ff @(posedge clk or negedge rst_n) begin
        if(!rst_n) begin
            state <= IDLE;
        end
        else begin
            state <= next_state;
        end
    end

    always_comb begin
        case(state) 
            IDLE: begin
                next_state = in?S1:IDLE;
            end 

            S1: begin
                next_state = in?S1:S10;
            end 

            S10: begin
                next_state = S10X;
            end 

            S10X: begin
                next_state = in?S1:S10X0;
            end 

            S10X0: begin
                next_state = in?S10X01:IDLE;
            end

            S10X01: begin
                next_state = in?FINAL:S10;
            end 

            FINAL: begin
                next_state = in?S1:S10;
            end  
            
            default : begin
                next_state = IDLE;
            end
        endcase
    end

    assign detect = (state == FINAL);

endmodule

module test;
    logic clk;
    logic rst_n;
    logic in;
    logic detect;
    logic  test_array[] = '{1,0,0,0,1,1,1,0,1,1,1,0,1,1,0,1,0,1,1,1,1,0,1,1,1,1,1,0,1,1,0,0,0,1};

    fsm dut(.*);

    initial clk = 0;
    always #5 clk = ~clk;

    initial begin
        $dumpfile("waves/fsm_10X011.vcd");
        $dumpvars(1, test);
    end

    initial begin
        rst_n = 0;
        in = 0;
        repeat(2) @(negedge clk);
        rst_n = 1;

        foreach(test_array[i]) begin
            @(negedge clk);
            in = test_array[i];

            @(posedge clk);
            #1;
            $display("TIME: %0t, in = %0b, detect = %0b, state = %0s",$time, in, detect, dut.state.name());
        end
        
        @(posedge clk);
        $finish;
    end

endmodule

fsm/waves/fsm_10X011.vcd
$date
    Sep  5, 2026  17:48:37
$end
$version
    TOOL:	xmsim	22.03-s012
$end
$timescale
    1 ns
$end

$scope module test $end
$var reg       1 !    clk $end
$var reg       1 "    rst_n $end
$var reg       1 #    in $end
$var reg       1 $    detect $end
$upscope $end

$enddefinitions $end
$dumpvars
0!
0"
0#
0$
$end
#5
1!
#10
0!
#15
1!
#20
0!
1"
#25
1!
#30
0!
1#
#35
1!
#40
0!
0#
#45
1!
#50
0!
#55
1!
#60
0!
#65
1!
#70
0!
1#
#75
1!
#80
0!
#85
1!
1$
#90
0!
#95
1!
0$
#100
0!
0#
#105
1!
#110
0!
1#
#115
1!
#120
0!
#125
1!
#130
0!
#135
1!
#140
0!
0#
#145
1!
#150
0!
1#
#155
1!
#160
0!
#165
1!
#170
0!
0#
#175
1!
#180
0!
1#
#185
1!
#190
0!
0#
#195
1!
#200
0!
1#
#205
1!
#210
0!
#215
1!
1$
#220
0!
#225
1!
0$
#230
0!
#235
1!
#240
0!
0#
#245
1!
#250
0!
1#
#255
1!
#260
0!
#265
1!
#270
0!
#275
1!
#280
0!
#285
1!
#290
0!
#295
1!
#300
0!
0#
#305
1!
#310
0!
1#
#315
1!
#320
0!
#325
1!
#330
0!
0#
#335
1!
#340
0!
#345
1!
#350
0!
#355
1!
#360
0!
1#
