fsm/twos_complement.sv
/**** Design a finite state machine FSM for a serial two’s complement block ****/

/******
To convert a normal representation to 2's complement representation we follow the following steps
1) Moving from LSB -> MSB, retain all the bits until a 1 is seen. Retain the 1 bit as well
2) Invert all the bits after the 1st one is seen

Example: 0111 (7 in binary unsigned representation)
1) Retain all bits till a 1 is seen: output => 1
2) Since we found 1 at the very first index, we retain and invert everything after that: output => 1001(-7 in signed 2's complement form)

Example: 0100 (4 in binary unsigned representation)
1) Retain all bits till 1 is seen: output => 100
2) Since we found 1 at index 2 from the lsb, we invert bits after that: output => 1100 (-4 in signed 2's complement form)

FSM Design
State A: We have not yet found the first 1 bit from the LSB
State B: We have found the first high bit (1),let's invert everything after that

State Transition Table
Current State | Input | Next State | Output
     A        |   0   |     A      |    0 
     A        |   1   |     B      |    1 
     B        |   0   |     B      |    1
     B        |   1   |     B      |    0

Next State = Current State or Input
Output = Current State xor Input

******/

module twos_complement(
     input clk,
     input rst_n,
     input in,
     output logic out
);

     logic state; // state A is logic 0 and state B is logic 1
     logic next_state;

     always_ff @(posedge clk or negedge rst_n) begin
          if(!rst_n) begin
               state <= 0;
          end
          else state <= next_state;
     end

     always_comb begin
          next_state = state | in;
          out = state ^ in;
     end
endmodule


// Reference model testbench
module test;

     logic clk;
     logic rst_n;
     logic in;
     logic out;

     twos_complement dut(.*);

     initial clk = 0;
     always #5 clk = ~clk;

     initial begin
          $dumpfile("waves/twos_complement.vcd");
          $dumpvars(1, test);
     end

     /**** Task to test a 4bit input word ****/
     task automatic test_word(input logic[3:0] word);

          logic[3:0] expected;       // Expected result of 2's complement for given input

          expected = (~word)+1; // 2's complement

          $display("Input word: %04b", word);
          $display("Expected word: %04b", expected);

          // Reset
          rst_n = 0;
          in = 0;
          repeat(2) @(posedge clk);
          rst_n = 1;
          @(posedge clk);
          for(int i =0;i<4;i++) begin
               @(negedge clk);
               in = word[i];

               #1;
               if(out != expected[i]) begin
                    $error("Bit %0d failed: in = %0b, out = %b, expected out = %b", i,in,out,expected[i]);
               end
               else begin
                    $display("Bit %0d passed: in = %0b, out = %b, expected out = %b", i,in,out,expected[i]);
               end
               @(posedge clk);
          end

     endtask

     initial begin
          in =0;
          rst_n =1;

          test_word(4'b0000);
          test_word(4'b0001);

          test_word(4'b0111);
          test_word(4'b0100);

          test_word(4'b0010);
          test_word(4'b0011);
          test_word(4'b0101);
          test_word(4'b1111);
          test_word(4'b1000);
          test_word(4'b1010);
          test_word(4'b1101);

          $finish;
     end
endmodule

fsm/waves/twos_complement.vcd
$date
    Aug  1, 2026  11:17:53
$end
$version
    TOOL:	xmsim	22.03-s012
$end
$timescale
    1 ns
$end

$scope module test $end
$var reg       1 !    clk $end
$var reg       1 "    rst_n $end
$var reg       1 #    in $end
$var reg       1 $    out $end
$upscope $end

$enddefinitions $end
$dumpvars
0!
0"
0#
0$
$end
#5
1!
#10
0!
#15
1!
1"
#20
0!
#25
1!
#30
0!
#35
1!
#40
0!
#45
1!
#50
0!
#55
1!
#60
0!
#65
1!
0"
#70
0!
#75
1!
#80
0!
#85
1!
1"
#90
0!
#95
1!
#100
0!
1#
1$
#105
1!
0$
#110
0!
0#
1$
#115
1!
#120
0!
#125
1!
#130
0!
#135
1!
0"
0$
#140
0!
#145
1!
#150
0!
#155
1!
1"
#160
0!
#165
1!
#170
0!
1#
1$
#175
1!
0$
#180
0!
#185
1!
#190
0!
#195
1!
#200
0!
0#
1$
#205
1!
0"
0$
#210
0!
#215
1!
#220
0!
#225
1!
1"
#230
0!
#235
1!
#240
0!
#245
1!
#250
0!
#255
1!
#260
0!
1#
1$
#265
1!
0$
#270
0!
0#
1$
#275
1!
0"
0$
#280
0!
#285
1!
#290
0!
#295
1!
1"
#300
0!
#305
1!
#310
0!
#315
1!
#320
0!
1#
1$
#325
1!
0$
#330
0!
0#
1$
#335
1!
#340
0!
#345
1!
0"
0$
#350
0!
#355
1!
#360
0!
#365
1!
1"
#370
0!
#375
1!
#380
0!
1#
1$
#385
1!
0$
#390
0!
#395
1!
#400
0!
0#
1$
#405
1!
#410
0!
#415
1!
0"
0$
#420
0!
#425
1!
#430
0!
#435
1!
1"
#440
0!
#445
1!
#450
0!
1#
1$
#455
1!
0$
#460
0!
0#
1$
#465
1!
#470
0!
1#
0$
#475
1!
#480
0!
0#
1$
#485
1!
0"
0$
#490
0!
#495
1!
#500
0!
#505
1!
1"
#510
0!
#515
1!
#520
0!
1#
1$
#525
1!
0$
#530
0!
#535
1!
#540
0!
#545
1!
#550
0!
#555
1!
0"
0#
1$
0$
#560
0!
#565
1!
#570
0!
#575
1!
1"
#580
0!
#585
1!
#590
0!
#595
1!
#600
0!
#605
1!
#610
0!
#615
1!
#620
0!
1#
1$
#625
1!
0"
0#
0$
#630
0!
#635
1!
#640
0!
#645
1!
1"
#650
0!
#655
1!
#660
0!
#665
1!
#670
0!
1#
1$
#675
1!
0$
#680
0!
0#
1$
#685
1!
#690
0!
1#
0$
#695
1!
0"
0#
1$
0$
#700
0!
#705
1!
#710
0!
#715
1!
1"
#720
0!
#725
1!
#730
0!
1#
1$
#735
1!
0$
#740
0!
0#
1$
#745
1!
#750
0!
1#
0$
